startme/__init__.py
startme/starter.py
startme/mods/__init__.py
startme/mods/internal/__init__.py
startme-0.0.15.data/scripts/startme
startme-0.0.15.dist-info/LICENSE
startme-0.0.15.dist-info/METADATA
startme-0.0.15.dist-info/WHEEL
startme-0.0.15.dist-info/top_level.txt
startme-0.0.15.dist-info/RECORD
