Metadata-Version: 2.1
Name: startme
Version: 0.0.15
Summary: systemd/cron alternative for python virtualenv
Home-page: https://github.com/yaroslaff/startme
Author: Yaroslav Polyakov
Author-email: yaroslaff@gmail.com
License: MIT
Platform: UNKNOWN
Classifier: Development Status :: 3 - Alpha
Classifier: Intended Audience :: Developers
Classifier: License :: OSI Approved :: MIT License
Classifier: Programming Language :: Python :: 3.6
Requires-Python: >=3.6
Requires-Dist: lightsleep (>=0.0.6)
